LICENSE
MANIFEST.in
README.md
setup.py
audit_ninja/__init__.py
audit_ninja/apps.py
audit_ninja/asgi.py
audit_ninja/backends.py
audit_ninja/constants.py
audit_ninja/managers.py
audit_ninja/settings.py
audit_ninja/urls.py
audit_ninja/utils.py
audit_ninja/wsgi.py
audit_ninja.egg-info/PKG-INFO
audit_ninja.egg-info/SOURCES.txt
audit_ninja.egg-info/dependency_links.txt
audit_ninja.egg-info/requires.txt
audit_ninja.egg-info/top_level.txt
audit_ninja/middleware/__init__.py
audit_ninja/middleware/audit_ninja.py
audit_ninja/middleware/middleware.py
audit_ninja/signals/__init__.py
audit_ninja/signals/auth_signals.py
audit_ninja/signals/crud_flows.py
audit_ninja/signals/model_signals.py
audit_ninja/signals/request_signals.py