Metadata-Version: 2.1
Name: audit_ninja
Version: 0.1.1
Summary: This is a auditing tool for Django Applications
Home-page: 
Author: Anand Singh
Author-email: anandi1990singh@gmail.com
Classifier: Programming Language :: Python :: 3
Classifier: Framework :: Django
Classifier: License :: OSI Approved :: MIT License
License-File: LICENSE
Requires-Dist: django
